tests/__init__.py
tests/test_normalize.py
tests/classifiers/__init__.py
tests/classifiers/classifier_base.py
tests/classifiers/test_amino_acid_deletion.py
tests/classifiers/test_amino_acid_delins.py
tests/classifiers/test_amino_acid_insertion.py
tests/classifiers/test_amino_acid_substitution.py
tests/classifiers/test_coding_dna_deletion.py
tests/classifiers/test_coding_dna_delins.py
tests/classifiers/test_coding_dna_insertion.py
tests/classifiers/test_coding_dna_silent_mutation.py
tests/classifiers/test_coding_dna_substitution.py
tests/classifiers/test_fusion.py
tests/classifiers/test_genomic_deletion.py
tests/classifiers/test_genomic_delins.py
tests/classifiers/test_genomic_insertion.py
tests/classifiers/test_genomic_silent_mutation.py
tests/classifiers/test_genomic_substitution.py
tests/classifiers/test_polypeptide_truncation.py
tests/classifiers/test_silent_mutation.py
tests/tokenizers/__init__.py
tests/tokenizers/test_amino_acid_deletion.py
tests/tokenizers/test_amino_acid_delins.py
tests/tokenizers/test_amino_acid_insertion.py
tests/tokenizers/test_amino_acid_substitution.py
tests/tokenizers/test_coding_dna_deletion.py
tests/tokenizers/test_coding_dna_delins.py
tests/tokenizers/test_coding_dna_insertion.py
tests/tokenizers/test_coding_dna_silent_mutation.py
tests/tokenizers/test_coding_dna_substitution.py
tests/tokenizers/test_fusion.py
tests/tokenizers/test_gene.py
tests/tokenizers/test_gene_pair.py
tests/tokenizers/test_genomic_deletion.py
tests/tokenizers/test_genomic_delins.py
tests/tokenizers/test_genomic_insertion.py
tests/tokenizers/test_genomic_silent_mutation.py
tests/tokenizers/test_genomic_substitution.py
tests/tokenizers/test_hgvs.py
tests/tokenizers/test_locus_reference_genomic.py
tests/tokenizers/test_polypeptide_truncation.py
tests/tokenizers/test_silent_mutation.py
tests/tokenizers/tokenizer_base.py
tests/translators/__init__.py
tests/translators/test_amino_acid_deletion.py
tests/translators/test_amino_acid_delins.py
variant_normalizer-0.2.4.dist-info/LICENSE
variant_normalizer-0.2.4.dist-info/METADATA
variant_normalizer-0.2.4.dist-info/WHEEL
variant_normalizer-0.2.4.dist-info/top_level.txt
variant_normalizer-0.2.4.dist-info/RECORD
