Metadata-Version: 2.1
Name: variant-normalizer
Version: 0.2.4
Summary: VICC normalization routine for variants
Home-page: https://github.com/cancervariants/variant-normalization
Author: VICC
Author-email: help@cancervariants.org
License: MIT
Platform: UNKNOWN
Classifier: Development Status :: 3 - Alpha
Classifier: Intended Audience :: Science/Research
Classifier: Intended Audience :: Developers
Classifier: Topic :: Scientific/Engineering :: Bio-Informatics
Classifier: License :: OSI Approved :: MIT License
Classifier: Programming Language :: Python :: 3
Classifier: Programming Language :: Python :: 3.7
Requires-Python: >=3.7
License-File: LICENSE
Requires-Dist: hgvs
Requires-Dist: requests
Requires-Dist: biocommons.seqrepo
Requires-Dist: fastapi
Requires-Dist: uvicorn
Requires-Dist: pydantic
Requires-Dist: ga4gh.vrs
Requires-Dist: gene-normalizer
